__init__.py
main.py
pyaccess/__init__.py
pyaccess/core.py
pyaccess/exceptions.py
pyaccess/models.py
pyaccess/backend/__init__.py
pyaccess/backend/base.py
pyaccess/backend/mdbtools_backend.py
pyaccess/backend/pyodbc_backend.py
pyaccess/geological/__init__.py
pyaccess/geological/collar.py
pyaccess/geological/database.py
pyaccess/geological/lithology.py
pyaccess/geological/survey.py
pyaccess-0.1.0a4.dist-info/METADATA
pyaccess-0.1.0a4.dist-info/WHEEL
pyaccess-0.1.0a4.dist-info/top_level.txt
pyaccess-0.1.0a4.dist-info/RECORD
