Metadata-Version: 2.4
Name: pyaccess
Version: 0.1.0a4
Summary: Python library for reading MS Access databases (.accdb/.mdb files) using pyodbc
Author-email: Lyralabs <developer@lyralabs.cloud>
Maintainer-email: Lyralabs <developer@lyralabs.cloud>
License-Expression: MIT
Project-URL: Homepage, https://github.com/rizquuula/pyaccess
Project-URL: Repository, https://github.com/rizquuula/pyaccess.git
Keywords: access,database,ms-access,mdb,accdb,pandas,geological,mining,mdbtools
Classifier: Development Status :: 4 - Beta
Classifier: Intended Audience :: Developers
Classifier: Intended Audience :: Science/Research
Classifier: Operating System :: Microsoft :: Windows
Classifier: Operating System :: POSIX :: Linux
Classifier: Operating System :: MacOS
Classifier: Programming Language :: Python :: 3
Classifier: Programming Language :: Python :: 3.11
Classifier: Programming Language :: Python :: 3.12
Classifier: Programming Language :: Python :: 3.13
Classifier: Topic :: Database
Classifier: Topic :: Scientific/Engineering :: Information Analysis
Classifier: Topic :: Software Development :: Libraries :: Python Modules
Requires-Python: >=3.11
Requires-Dist: pandas>=2.0.0
Requires-Dist: pip>=25.3
Requires-Dist: pyodbc>=5.0.0; sys_platform == "win32"
Requires-Dist: typing-extensions>=4.0.0
Requires-Dist: sqlalchemy>=2.0.0; sys_platform == "win32"
Requires-Dist: sqlalchemy-access>=2.0.0; sys_platform == "win32"
